odoo/addons/pos_disable_change_cashier/README.rst
odoo/addons/pos_disable_change_cashier/__init__.py
odoo/addons/pos_disable_change_cashier/__manifest__.py
odoo/addons/pos_disable_change_cashier/i18n/fr.po
odoo/addons/pos_disable_change_cashier/i18n/pos_disable_change_cashier.pot
odoo/addons/pos_disable_change_cashier/models/__init__.py
odoo/addons/pos_disable_change_cashier/models/pos_config.py
odoo/addons/pos_disable_change_cashier/readme/CONFIGURE.rst
odoo/addons/pos_disable_change_cashier/readme/CONTRIBUTORS.rst
odoo/addons/pos_disable_change_cashier/readme/DESCRIPTION.rst
odoo/addons/pos_disable_change_cashier/static/description/icon.png
odoo/addons/pos_disable_change_cashier/static/description/index.html
odoo/addons/pos_disable_change_cashier/static/description/pos_config_form.png
odoo/addons/pos_disable_change_cashier/static/src/js/chrome.js
odoo/addons/pos_disable_change_cashier/views/assets.xml
odoo/addons/pos_disable_change_cashier/views/pos_config.xml
odoo12_addon_pos_disable_change_cashier-12.0.1.0.1.dist-info/METADATA
odoo12_addon_pos_disable_change_cashier-12.0.1.0.1.dist-info/WHEEL
odoo12_addon_pos_disable_change_cashier-12.0.1.0.1.dist-info/top_level.txt
odoo12_addon_pos_disable_change_cashier-12.0.1.0.1.dist-info/RECORD
